universal_ml_framework/__init__.py
universal_ml_framework/configs/__init__.py
universal_ml_framework/configs/dataset_configs.py
universal_ml_framework/core/__init__.py
universal_ml_framework/core/pipeline.py
universal_ml_framework/utils/__init__.py
universal_ml_framework/utils/data_generator.py
universal_ml_framework/utils/helpers.py
universal_ml_framework-1.2.0.dist-info/licenses/LICENSE
universal_ml_framework-1.2.0.dist-info/METADATA
universal_ml_framework-1.2.0.dist-info/WHEEL
universal_ml_framework-1.2.0.dist-info/entry_points.txt
universal_ml_framework-1.2.0.dist-info/top_level.txt
universal_ml_framework-1.2.0.dist-info/RECORD
