Metadata-Version: 2.4
Name: universal-ml-framework
Version: 1.2.0
Summary: A complete machine learning pipeline framework for any dataset
Home-page: https://github.com/FathanAkram-App/universal-ml-framework
Author: Fathan Akram
Author-email: fathan.a.dev@gmail.com
Project-URL: Bug Reports, https://github.com/FathanAkram-App/universal-ml-framework/issues
Project-URL: Source, https://github.com/FathanAkram-App/universal-ml-framework
Project-URL: Documentation, https://universal-ml-framework.readthedocs.io/
Keywords: machine learning,pipeline,automation,classification,regression,data science
Classifier: Development Status :: 4 - Beta
Classifier: Intended Audience :: Developers
Classifier: Intended Audience :: Science/Research
Classifier: License :: OSI Approved :: MIT License
Classifier: Operating System :: OS Independent
Classifier: Programming Language :: Python :: 3
Classifier: Programming Language :: Python :: 3.7
Classifier: Programming Language :: Python :: 3.8
Classifier: Programming Language :: Python :: 3.9
Classifier: Programming Language :: Python :: 3.10
Classifier: Topic :: Scientific/Engineering :: Artificial Intelligence
Classifier: Topic :: Software Development :: Libraries :: Python Modules
Requires-Python: >=3.7
License-File: LICENSE
Requires-Dist: pandas>=1.3.0
Requires-Dist: scikit-learn>=1.0.0
Requires-Dist: numpy>=1.21.0
Requires-Dist: joblib>=1.0.0
Provides-Extra: dev
Requires-Dist: pytest>=6.0; extra == "dev"
Requires-Dist: black>=21.0; extra == "dev"
Requires-Dist: flake8>=3.9; extra == "dev"
Requires-Dist: jupyter>=1.0; extra == "dev"
Provides-Extra: viz
Requires-Dist: matplotlib>=3.3.0; extra == "viz"
Requires-Dist: seaborn>=0.11.0; extra == "viz"
Requires-Dist: plotly>=5.0.0; extra == "viz"
Dynamic: author
Dynamic: author-email
Dynamic: classifier
Dynamic: description
Dynamic: description-content-type
Dynamic: home-page
Dynamic: keywords
Dynamic: license-file
Dynamic: project-url
Dynamic: provides-extra
Dynamic: requires-dist
Dynamic: requires-python
Dynamic: summary
